pgmydemo/__init__.py
pgmydemo/lap1.py
pgmydemo/sob1.py
test/__init__.py
test/test.py
pgmydemo-0.1.0.dist-info/METADATA
pgmydemo-0.1.0.dist-info/WHEEL
pgmydemo-0.1.0.dist-info/top_level.txt
pgmydemo-0.1.0.dist-info/RECORD
