Metadata-Version: 2.1
Name: pgmydemo
Version: 0.1.0
Summary: leo function
Author: leo
Author-email: your_email@example.com
Classifier: Programming Language :: Python :: 3
Classifier: License :: OSI Approved :: MIT License
Classifier: Operating System :: OS Independent
Requires-Dist: numpy (>=1.24.0)
Requires-Dist: opencv-python (>=4.10.0)
